dataintegrityfingerprint/__init__.py
dataintegrityfingerprint/__main__.py
dataintegrityfingerprint/cli.py
dataintegrityfingerprint/dif.py
dataintegrityfingerprint/gui.py
dataintegrityfingerprint/openssl_hash_algorithm.py
dataintegrityfingerprint/zlib_hash_algorithm.py
dataintegrityfingerprint-0.7.6.dist-info/LICENSE
dataintegrityfingerprint-0.7.6.dist-info/METADATA
dataintegrityfingerprint-0.7.6.dist-info/WHEEL
dataintegrityfingerprint-0.7.6.dist-info/entry_points.txt
dataintegrityfingerprint-0.7.6.dist-info/top_level.txt
dataintegrityfingerprint-0.7.6.dist-info/RECORD
