Metadata-Version: 2.1
Name: dataintegrityfingerprint
Version: 0.7.6
Summary: Data Integrity Fingerprint (DIF) - A reference implementation in Python
Home-page: https://github.com/expyriment/dataintegrityfingerprint-python
Author: Oliver Lindemann, Florian Krause
Author-email: oliver@expyriment.org, florian@expyriment.org
License: UNKNOWN
Platform: UNKNOWN
Classifier: Intended Audience :: Education
Classifier: Intended Audience :: Science/Research
Classifier: License :: OSI Approved :: MIT License
Classifier: Operating System :: OS Independent
Classifier: Programming Language :: Python
Classifier: Programming Language :: Python :: 3
Classifier: Topic :: Scientific/Engineering
Requires-Python: >=3.6
License-File: LICENSE
